zenml/README.md
zenml/VERSION
zenml/__init__.py
zenml/actions/__init__.py
zenml/actions/base_action.py
zenml/actions/pipeline_run/__init__.py
zenml/actions/pipeline_run/pipeline_run_action.py
zenml/alerter/__init__.py
zenml/alerter/base_alerter.py
zenml/analytics/__init__.py
zenml/analytics/client.py
zenml/analytics/context.py
zenml/analytics/enums.py
zenml/analytics/models.py
zenml/analytics/request.py
zenml/analytics/utils.py
zenml/annotators/__init__.py
zenml/annotators/base_annotator.py
zenml/artifact_stores/__init__.py
zenml/artifact_stores/base_artifact_store.py
zenml/artifact_stores/local_artifact_store.py
zenml/artifacts/__init__.py
zenml/artifacts/artifact_config.py
zenml/artifacts/external_artifact.py
zenml/artifacts/external_artifact_config.py
zenml/artifacts/in_memory_cache.py
zenml/artifacts/preexisting_data_materializer.py
zenml/artifacts/unmaterialized_artifact.py
zenml/artifacts/utils.py
zenml/cli/AGENTS.md
zenml/cli/__init__.py
zenml/cli/annotator.py
zenml/cli/artifact.py
zenml/cli/authorized_device.py
zenml/cli/base.py
zenml/cli/cli.py
zenml/cli/code_repository.py
zenml/cli/config.py
zenml/cli/deployment.py
zenml/cli/downgrade.py
zenml/cli/feature.py
zenml/cli/formatter.py
zenml/cli/integration.py
zenml/cli/login.py
zenml/cli/model.py
zenml/cli/model_registry.py
zenml/cli/pipeline.py
zenml/cli/project.py
zenml/cli/secret.py
zenml/cli/served_model.py
zenml/cli/server.py
zenml/cli/service_accounts.py
zenml/cli/service_connectors.py
zenml/cli/stack.py
zenml/cli/stack_components.py
zenml/cli/tag.py
zenml/cli/text_utils.py
zenml/cli/user_management.py
zenml/cli/utils.py
zenml/cli/version.py
zenml/client.py
zenml/client_lazy_loader.py
zenml/code_repositories/__init__.py
zenml/code_repositories/base_code_repository.py
zenml/code_repositories/git/__init__.py
zenml/code_repositories/git/local_git_repository_context.py
zenml/code_repositories/local_repository_context.py
zenml/config/__init__.py
zenml/config/base_settings.py
zenml_nightly-0.93.1.dev20260115.dist-info/WHEEL
zenml_nightly-0.93.1.dev20260115.dist-info/entry_points.txt
zenml_nightly-0.93.1.dev20260115.dist-info/METADATA
zenml_nightly-0.93.1.dev20260115.dist-info/RECORD
