Metadata-Version: 2.4
Name: zenml-nightly
Version: 0.93.1.dev20260115
Summary: ZenML: MLOps for Reliable AI: from Classical AI to Agents.
Keywords: machine learning,production,pipeline,mlops,devops,ai,agents,agentic workflows
Author: ZenML GmbH
Author-email: ZenML GmbH <info@zenml.io>
License-Expression: Apache-2.0
Classifier: Development Status :: 4 - Beta
Classifier: Intended Audience :: Developers
Classifier: Intended Audience :: Science/Research
Classifier: Intended Audience :: System Administrators
Classifier: License :: OSI Approved :: Apache Software License
Classifier: Programming Language :: Python :: 3 :: Only
Classifier: Programming Language :: Python :: 3.10
Classifier: Programming Language :: Python :: 3.11
Classifier: Programming Language :: Python :: 3.12
Classifier: Programming Language :: Python :: 3.13
Classifier: Topic :: System :: Distributed Computing
Classifier: Topic :: Software Development :: Libraries :: Python Modules
Classifier: Typing :: Typed
Requires-Dist: asgiref~=3.10.0
Requires-Dist: click>=8.0.1,<=8.2.1
Requires-Dist: cloudpickle>=2.0.0
Requires-Dist: distro>=1.6.0,<2.0.0
Requires-Dist: docker~=7.1.0
Requires-Dist: gitpython>=3.1.18,<4.0.0
Requires-Dist: jsonref
Requires-Dist: opentelemetry-sdk==1.38.0
Requires-Dist: packaging>=24.1
Requires-Dist: psutil>=5.0.0
Requires-Dist: pydantic>=2.0,<=2.11.9
Requires-Dist: python-dateutil>=2.8.1,<3.0.0
Requires-Dist: pyyaml>=6.0.1
Requires-Dist: rich>=12.0.0
Requires-Dist: setuptools>=70.0.0
Requires-Dist: adlfs>=2021.10.0 ; extra == 'adlfs'
Requires-Dist: azure-ai-ml==1.23.1 ; extra == 'azureml'
Requires-Dist: boto3>=1.16.0 ; extra == 'connectors-aws'
Requires-Dist: kubernetes>=18.20.0 ; extra == 'connectors-aws'
Requires-Dist: aws-profile-manager>=0.5.0 ; extra == 'connectors-aws'
Requires-Dist: azure-identity>=1.4.0 ; extra == 'connectors-azure'
Requires-Dist: azure-mgmt-containerservice>=20.0.0 ; extra == 'connectors-azure'
Requires-Dist: azure-mgmt-containerregistry>=10.0.0 ; extra == 'connectors-azure'
Requires-Dist: azure-mgmt-storage>=20.0.0 ; extra == 'connectors-azure'
Requires-Dist: azure-storage-blob>=12.0.0 ; extra == 'connectors-azure'
Requires-Dist: azure-mgmt-resource>=21.0.0 ; extra == 'connectors-azure'
Requires-Dist: kubernetes>=18.20.0 ; extra == 'connectors-azure'
Requires-Dist: requests>=2.27.11,<3.0.0 ; extra == 'connectors-azure'
Requires-Dist: marshmallow<4.0.0 ; extra == 'connectors-azure'
Requires-Dist: google-cloud-container>=2.21.0 ; extra == 'connectors-gcp'
Requires-Dist: google-cloud-storage>=2.9.0 ; extra == 'connectors-gcp'
Requires-Dist: google-cloud-artifact-registry>=1.11.3 ; extra == 'connectors-gcp'
Requires-Dist: kubernetes>=18.20.0 ; extra == 'connectors-gcp'
Requires-Dist: kubernetes>=18.20.0 ; extra == 'connectors-kubernetes'
Requires-Dist: bandit>=1.7.5,<2.0.0 ; extra == 'dev'
Requires-Dist: ruff>=0.1.7 ; extra == 'dev'
Requires-Dist: yamlfix>=1.16.0 ; extra == 'dev'
Requires-Dist: coverage[toml]>=5.5,<6.0.0 ; extra == 'dev'
Requires-Dist: pytest>=7.4.0,<8.0.0 ; extra == 'dev'
Requires-Dist: mypy==1.18.1 ; extra == 'dev'
Requires-Dist: pre-commit ; extra == 'dev'
Requires-Dist: pyment>=0.3.3,<0.4.0 ; extra == 'dev'
Requires-Dist: tox>=3.24.3 ; extra == 'dev'
Requires-Dist: hypothesis>=6.43.1 ; extra == 'dev'
Requires-Dist: typing-extensions>=3.7.4 ; extra == 'dev'
Requires-Dist: darglint>=1.8.1 ; extra == 'dev'
Requires-Dist: pytest-randomly>=3.10.1,<4.0.0 ; extra == 'dev'
Requires-Dist: pytest-mock>=3.6.1,<4.0.0 ; extra == 'dev'
Requires-Dist: pytest-clarity>=1.0.1,<2.0.0 ; extra == 'dev'
Requires-Dist: pytest-instafail>=0.5.0 ; extra == 'dev'
Requires-Dist: pytest-rerunfailures>=13.0,<14.0.0 ; extra == 'dev'
Requires-Dist: pytest-split>=0.10.0,<0.11.0 ; extra == 'dev'
Requires-Dist: mkdocs>=1.6.1,<2.0.0 ; extra == 'dev'
Requires-Dist: mkdocs-material==9.6.8 ; extra == 'dev'
Requires-Dist: mkdocs-awesome-pages-plugin>=2.10.1,<3.0.0 ; extra == 'dev'
Requires-Dist: mkdocstrings[python]>=0.28.1,<1.0.0 ; extra == 'dev'
Requires-Dist: mkdocstrings-python ; extra == 'dev'
Requires-Dist: mkdocs-autorefs>=1.4.0,<2.0.0 ; extra == 'dev'
Requires-Dist: mike>=1.1.2,<2.0.0 ; extra == 'dev'
Requires-Dist: maison<2.0 ; extra == 'dev'
Requires-Dist: types-certifi>=2021.10.8.0 ; extra == 'dev'
Requires-Dist: types-croniter>=1.0.2 ; extra == 'dev'
Requires-Dist: types-futures>=3.3.1 ; extra == 'dev'
Requires-Dist: types-hvac>=2.3.0 ; extra == 'dev'
Requires-Dist: types-markdown>=3.3.6 ; extra == 'dev'
Requires-Dist: types-paramiko>=3.4.0,<4.0.0 ; extra == 'dev'
Requires-Dist: types-pillow>=9.2.1 ; extra == 'dev'
Requires-Dist: types-protobuf>=3.18.0 ; extra == 'dev'
Requires-Dist: types-pymysql>=1.0.4 ; extra == 'dev'
Requires-Dist: types-python-dateutil>=2.8.2 ; extra == 'dev'
Requires-Dist: types-python-slugify>=5.0.2 ; extra == 'dev'
Requires-Dist: types-pyyaml>=6.0.0 ; extra == 'dev'
Requires-Dist: types-redis>=4.1.19 ; extra == 'dev'
Requires-Dist: types-requests>=2.27.11 ; extra == 'dev'
Requires-Dist: types-setuptools>=57.4.2 ; extra == 'dev'
Requires-Dist: types-six>=1.16.2 ; extra == 'dev'
Requires-Dist: types-termcolor>=1.1.2 ; extra == 'dev'
Requires-Dist: types-psutil>=5.8.13 ; extra == 'dev'
Requires-Dist: types-passlib>=1.7.7 ; extra == 'dev'
Requires-Dist: gcsfs>=2022.11.0 ; extra == 'gcsfs'
Requires-Dist: rich[jupyter]>=12.0.0 ; extra == 'jupyter'
Requires-Dist: alembic>=1.8.1,<=1.15.2 ; extra == 'local'
Requires-Dist: bcrypt==4.0.1 ; extra == 'local'
Requires-Dist: passlib[bcrypt]~=1.7.4 ; extra == 'local'
Requires-Dist: pymysql~=1.1.0,>=1.1.1 ; extra == 'local'
Requires-Dist: sqlalchemy>=2.0.0,<3.0.0 ; extra == 'local'
Requires-Dist: sqlalchemy-utils ; extra == 'local'
Requires-Dist: sqlmodel==0.0.18 ; extra == 'local'
Requires-Dist: s3fs>=2022.11.0,!=2025.3.1 ; extra == 's3fs'
Requires-Dist: sagemaker>=2.237.3,<3.0.0 ; extra == 'sagemaker'
Requires-Dist: boto3>=1.16.0 ; extra == 'secrets-aws'
Requires-Dist: azure-identity>=1.4.0 ; extra == 'secrets-azure'
Requires-Dist: azure-keyvault-secrets>=4.0.0 ; extra == 'secrets-azure'
Requires-Dist: google-cloud-secret-manager>=2.12.5 ; extra == 'secrets-gcp'
Requires-Dist: hvac>=0.11.2 ; extra == 'secrets-hashicorp'
Requires-Dist: zenml[local] ; extra == 'server'
Requires-Dist: fastapi>=0.100,<=0.115.8 ; extra == 'server'
Requires-Dist: uvicorn[standard]>=0.17.5 ; extra == 'server'
Requires-Dist: python-multipart~=0.0.9 ; extra == 'server'
Requires-Dist: pyjwt[crypto]==2.7.* ; extra == 'server'
Requires-Dist: fastapi-utils ; extra == 'server'
Requires-Dist: orjson~=3.10.0 ; extra == 'server'
Requires-Dist: jinja2 ; extra == 'server'
Requires-Dist: ipinfo>=4.4.3 ; extra == 'server'
Requires-Dist: secure~=1.0.1 ; extra == 'server'
Requires-Dist: tldextract~=5.1.0 ; extra == 'server'
Requires-Dist: itsdangerous~=2.2.0 ; extra == 'server'
Requires-Dist: copier>=8.1.0 ; extra == 'templates'
Requires-Dist: jinja2-time>=0.2.0,<0.3.0 ; extra == 'templates'
Requires-Dist: ruff>=0.1.7 ; extra == 'templates'
Requires-Dist: pyyaml-include<2.0 ; extra == 'templates'
Requires-Dist: python-terraform ; extra == 'terraform'
Requires-Dist: google-cloud-aiplatform>=1.34.0 ; extra == 'vertex'
Requires-Dist: kfp>=2.6.0 ; extra == 'vertex'
Requires-Dist: urllib3<2.6.0 ; extra == 'vertex'
Requires-Dist: google-cloud-pipeline-components>=2.19.0 ; extra == 'vertex'
Requires-Python: >=3.10, <3.14
Project-URL: Documentation, https://docs.zenml.io
Project-URL: Homepage, https://zenml.io
Project-URL: Issues, https://github.com/zenml-io/zenml/issues
Project-URL: Repository, https://github.com/zenml-io/zenml
Provides-Extra: adlfs
Provides-Extra: azureml
Provides-Extra: connectors-aws
Provides-Extra: connectors-azure
Provides-Extra: connectors-gcp
Provides-Extra: connectors-kubernetes
Provides-Extra: dev
Provides-Extra: gcsfs
Provides-Extra: jupyter
Provides-Extra: local
Provides-Extra: s3fs
Provides-Extra: sagemaker
Provides-Extra: secrets-aws
Provides-Extra: secrets-azure
Provides-Extra: secrets-gcp
Provides-Extra: secrets-hashicorp
Provides-Extra: server
Provides-Extra: templates
Provides-Extra: terraform
Provides-Extra: vertex
